dpyseriesformatter/__init__.py
dpy_seriesformatter-0.0.1.dist-info/LICENSE
dpy_seriesformatter-0.0.1.dist-info/METADATA
dpy_seriesformatter-0.0.1.dist-info/WHEEL
dpy_seriesformatter-0.0.1.dist-info/top_level.txt
dpy_seriesformatter-0.0.1.dist-info/RECORD
